merge/__init__.py
merge/merge.py
code_merger-1.0.2.dist-info/LICENSE
code_merger-1.0.2.dist-info/METADATA
code_merger-1.0.2.dist-info/WHEEL
code_merger-1.0.2.dist-info/entry_points.txt
code_merger-1.0.2.dist-info/top_level.txt
code_merger-1.0.2.dist-info/RECORD
