Metadata-Version: 2.1
Name: code-merger
Version: 1.0.2
Summary: A tool for merging code files into a single markdown document.
Home-page: https://github.com/raphael2692/code-merger
Author: Raffaele Spataro
Author-email: raffaele2692@gmail.com
Classifier: Programming Language :: Python :: 3
Classifier: License :: OSI Approved :: MIT License
Classifier: Operating System :: OS Independent
Requires-Python: >=3.6
License-File: LICENSE
